cdk8s_plus_23/__init__.py
cdk8s_plus_23/py.typed
cdk8s_plus_23/_jsii/__init__.py
cdk8s_plus_23/_jsii/cdk8s-plus-23@2.4.25.jsii.tgz
cdk8s_plus_23/k8s/__init__.py
cdk8s_plus_23-2.4.25.dist-info/LICENSE
cdk8s_plus_23-2.4.25.dist-info/METADATA
cdk8s_plus_23-2.4.25.dist-info/NOTICE
cdk8s_plus_23-2.4.25.dist-info/WHEEL
cdk8s_plus_23-2.4.25.dist-info/top_level.txt
cdk8s_plus_23-2.4.25.dist-info/RECORD
