Metadata-Version: 2.1
Name: cdk8s-plus-23
Version: 2.4.25
Summary: cdk8s+ is a software development framework that provides high level abstractions for authoring Kubernetes applications. cdk8s-plus-23 synthesizes Kubernetes manifests for Kubernetes 1.23.0
Home-page: https://github.com/cdk8s-team/cdk8s-plus.git
Author: Amazon Web Services
License: Apache-2.0
Project-URL: Source, https://github.com/cdk8s-team/cdk8s-plus.git
Classifier: Intended Audience :: Developers
Classifier: Operating System :: OS Independent
Classifier: Programming Language :: JavaScript
Classifier: Programming Language :: Python :: 3 :: Only
Classifier: Programming Language :: Python :: 3.7
Classifier: Programming Language :: Python :: 3.8
Classifier: Programming Language :: Python :: 3.9
Classifier: Programming Language :: Python :: 3.10
Classifier: Typing :: Typed
Classifier: Development Status :: 5 - Production/Stable
Classifier: License :: OSI Approved
Requires-Python: ~=3.7
License-File: LICENSE
License-File: NOTICE
Requires-Dist: cdk8s (<3.0.0,>=2.7.4)
Requires-Dist: constructs (<11.0.0,>=10.1.254)
Requires-Dist: jsii (<2.0.0,>=1.75.0)
Requires-Dist: publication (>=0.0.3)
Requires-Dist: typeguard (~=2.13.3)
